{
  "currencies": [
    {
      "id": "divine",
      "name": "Divine Orb",
      "volume": 78021857,
      "pair_count": 21,
      "popularity_score": 99.5,
      "supported": true
    },
    {
      "id": "mirror",
      "name": "Mirror of Kalandra",
      "volume": 12670193,
      "pair_count": 2,
      "popularity_score": 57.62,
      "supported": true
    },
    {
      "id": "omen_whittling",
      "name": "Omen of Whittling",
      "volume": 8340780,
      "pair_count": 1,
      "popularity_score": 54.35,
      "supported": true
    },
    {
      "id": "annulment",
      "name": "Orb of Annulment",
      "volume": 8621252,
      "pair_count": 2,
      "popularity_score": 54.02,
      "supported": true
    },
    {
      "id": "hinekora_lock",
      "name": "Hinekora's Lock",
      "volume": 8299038,
      "pair_count": 2,
      "popularity_score": 53.32,
      "supported": true
    },
    {
      "id": "chaos",
      "name": "Chaos Orb",
      "volume": 7042239,
      "pair_count": 1,
      "popularity_score": 52.01,
      "supported": true
    },
    {
      "id": "omen_light",
      "name": "Omen of Light",
      "volume": 6196707,
      "pair_count": 1,
      "popularity_score": 50.97,
      "supported": true
    },
    {
      "id": "exalted",
      "name": "Exalted Orb",
      "volume": 6181844,
      "pair_count": 2,
      "popularity_score": 50.46,
      "supported": true
    },
    {
      "id": "perfect_exalted",
      "name": "Perfect Exalted Orb",
      "volume": 3838355,
      "pair_count": 1,
      "popularity_score": 48.46,
      "supported": true
    },
    {
      "id": "omen_of_sinistral_annulment",
      "name": "Omen of Sinistral Annulment",
      "volume": 2638266,
      "pair_count": 1,
      "popularity_score": 47.19,
      "supported": true
    },
    {
      "id": "ancient_jawbone",
      "name": "Ancient Jawbone",
      "volume": 2461309,
      "pair_count": 1,
      "popularity_score": 46.58,
      "supported": true
    },
    {
      "id": "rakiata_flow",
      "name": "Rakiata's Flow",
      "volume": 1856438,
      "pair_count": 1,
      "popularity_score": 45.69,
      "supported": true
    },
    {
      "id": "farrul_rune",
      "name": "Farrul's Rune of the Chase",
      "volume": 1802386,
      "pair_count": 1,
      "popularity_score": 45.16,
      "supported": true
    },
    {
      "id": "talisman_sirrius",
      "name": "Talisman of Sirrius",
      "volume": 1731603,
      "pair_count": 1,
      "popularity_score": 44.61,
      "supported": true
    },
    {
      "id": "diallas_desire",
      "name": "Dialla's Desire",
      "volume": 1572664,
      "pair_count": 1,
      "popularity_score": 44.01,
      "supported": true
    },
    {
      "id": "omen_of_sinistral_erasure",
      "name": "Omen of Sinistral Erasure",
      "volume": 1444611,
      "pair_count": 1,
      "popularity_score": 43.43,
      "supported": true
    },
    {
      "id": "hedgewitch_assandras_rune_of_wisdom",
      "name": "Hedgewitch Assandra's Rune of Wisdom",
      "volume": 1422733,
      "pair_count": 1,
      "popularity_score": 42.91,
      "supported": true
    },
    {
      "id": "essence_of_horror",
      "name": "Essence of Horror",
      "volume": 1316559,
      "pair_count": 1,
      "popularity_score": 42.34,
      "supported": true
    },
    {
      "id": "perfect_chaos",
      "name": "Perfect Chaos Orb",
      "volume": 1304333,
      "pair_count": 1,
      "popularity_score": 41.84,
      "supported": true
    },
    {
      "id": "omen_of_dextral_annulment",
      "name": "Omen of Dextral Annulment",
      "volume": 1036002,
      "pair_count": 1,
      "popularity_score": 41.16,
      "supported": true
    },
    {
      "id": "omen_of_dextral_erasure",
      "name": "Omen of Dextral Erasure",
      "volume": 977445,
      "pair_count": 1,
      "popularity_score": 40.13,
      "supported": true
    },
    {
      "id": "atalui_bloodletting",
      "name": "Atalui's Bloodletting",
      "volume": 906662,
      "pair_count": 1,
      "popularity_score": 39.08,
      "supported": true
    }
  ],
  "total": 22,
  "source": "poe2scout",
  "league": "Rise of the Abyssal",
  "fetched_at": "2025-10-09T05:11:37.274063Z",
  "metadata": {
    "scraper": "github-actions",
    "version": "1.0",
    "top_percentage": 1.0
  }
}