{
  "rates": {
    "mirror": {
      "divine": 1672.27
    },
    "divine": {
      "chaos": 32.04,
      "exalted": 967.17
    },
    "omen_light": {
      "divine": 3.88,
      "chaos": 114.83,
      "exalted": 2743.32
    },
    "annulment": {
      "divine": 0.41,
      "exalted": 322.12
    },
    "omen_whittling": {
      "divine": 3.6,
      "chaos": 105.77
    },
    "hinekora_lock": {
      "divine": 500.79
    },
    "perfect_exalted": {
      "divine": 1.84
    },
    "ancient_jawbone": {
      "divine": 4.13
    },
    "omen_of_dextral_annulment": {
      "divine": 5.35
    },
    "omen_of_sinistral_annulment": {
      "divine": 6.78
    },
    "rakiata_flow": {
      "divine": 18.82
    },
    "hedgewitch_assandras_rune_of_wisdom": {
      "divine": 21.64
    },
    "farrul_rune": {
      "divine": 9.63
    },
    "atalui_bloodletting": {
      "divine": 12.55
    },
    "diallas_desire": {
      "divine": 28.89
    },
    "perfect_chaos": {
      "divine": 2.73
    },
    "omen_of_dextral_erasure": {
      "divine": 2.79
    },
    "uhtreds_augury": {
      "divine": 66.8
    },
    "essence_of_horror": {
      "divine": 2.78
    }
  },
  "metadata": {
    "source": "poe2scout",
    "league": "Rise of the Abyssal",
    "fetched_at": "2025-10-15T01:13:03.212159Z",
    "ttl_seconds": 300,
    "total_pairs": 24
  }
}